pynetdicom/__init__.py
pynetdicom/__main__.py
pynetdicom/_config.py
pynetdicom/_globals.py
pynetdicom/_handlers.py
pynetdicom/_validators.py
pynetdicom/_version.py
pynetdicom/acse.py
pynetdicom/ae.py
pynetdicom/association.py
pynetdicom/dimse.py
pynetdicom/dimse_messages.py
pynetdicom/dimse_primitives.py
pynetdicom/dsutils.py
pynetdicom/dul.py
pynetdicom/events.py
pynetdicom/fsm.py
pynetdicom/pdu.py
pynetdicom/pdu_items.py
pynetdicom/pdu_primitives.py
pynetdicom/presentation.py
pynetdicom/py.typed
pynetdicom/service_class.py
pynetdicom/service_class_n.py
pynetdicom/sop_class.py
pynetdicom/status.py
pynetdicom/timer.py
pynetdicom/transport.py
pynetdicom/utils.py
pynetdicom/apps/__init__.py
pynetdicom/apps/common.py
pynetdicom/apps/echoscp/__init__.py
pynetdicom/apps/echoscp/echoscp.py
pynetdicom/apps/echoscu/__init__.py
pynetdicom/apps/echoscu/echoscu.py
pynetdicom/apps/findscu/__init__.py
pynetdicom/apps/findscu/findscu.py
pynetdicom/apps/getscu/__init__.py
pynetdicom/apps/getscu/getscu.py
pynetdicom/apps/movescu/__init__.py
pynetdicom/apps/movescu/movescu.py
pynetdicom/apps/qrscp/__init__.py
pynetdicom/apps/qrscp/db.py
pynetdicom/apps/qrscp/default.ini
pynetdicom/apps/qrscp/handlers.py
pynetdicom/apps/qrscp/qrscp.py
pynetdicom/apps/storescp/__init__.py
pynetdicom/apps/storescp/storescp.py
pynetdicom/apps/storescu/__init__.py
pynetdicom/apps/storescu/storescu.py
pynetdicom/apps/tests/__init__.py
pynetdicom/apps/tests/test_common.py
pynetdicom/apps/tests/test_echoscp.py
pynetdicom/apps/tests/test_echoscu.py
pynetdicom/apps/tests/test_findscu.py
pynetdicom/apps/tests/test_getscu.py
pynetdicom/apps/tests/test_movescu.py
pynetdicom/apps/tests/test_qrscp_db.py
pynetdicom/apps/tests/test_qrscp_echo.py
pynetdicom/apps/tests/test_qrscp_find.py
pynetdicom/apps/tests/test_qrscp_get.py
pynetdicom/apps/tests/test_qrscp_move.py
pynetdicom/apps/tests/test_qrscp_store.py
pynetdicom/apps/tests/test_storescp.py
pynetdicom/apps/tests/test_storescu.py
pynetdicom-3.0.3.dist-info/entry_points.txt
pynetdicom-3.0.3.dist-info/licenses/LICENCE
pynetdicom-3.0.3.dist-info/WHEEL
pynetdicom-3.0.3.dist-info/METADATA
pynetdicom-3.0.3.dist-info/RECORD
