Metadata-Version: 2.4
Name: pynetdicom
Version: 3.0.3
Summary: A Python implementation of the DICOM networking protocol
Keywords: dicom,networking,pydicom
Author: pynetdicom contributors
Maintainer-email: scaramallion <scaramallion@users.noreply.github.com>
Requires-Python: >=3.10
Classifier: License :: OSI Approved :: MIT License
Classifier: Intended Audience :: Developers
Classifier: Intended Audience :: Healthcare Industry
Classifier: Intended Audience :: Science/Research
Classifier: Development Status :: 5 - Production/Stable
Classifier: Natural Language :: English
Classifier: Programming Language :: Python :: 3.10
Classifier: Programming Language :: Python :: 3.11
Classifier: Programming Language :: Python :: 3.12
Classifier: Programming Language :: Python :: 3.13
Classifier: Operating System :: OS Independent
Classifier: Topic :: Scientific/Engineering :: Medical Science Apps.
Classifier: Topic :: Software Development :: Libraries
License-File: LICENCE
Requires-Dist: pydicom >=3, <4
Requires-Dist: sqlalchemy ; extra == "apps"
Requires-Dist: asv >=0.6 ; extra == "dev"
Requires-Dist: black >=23.1 ; extra == "dev"
Requires-Dist: codespell >=2.2 ; extra == "dev"
Requires-Dist: coverage >=7.3 ; extra == "dev"
Requires-Dist: mypy >= 1.11 ; extra == "dev"
Requires-Dist: pyfakefs >=5.3 ; extra == "dev"
Requires-Dist: pytest >=7.4 ; extra == "dev"
Requires-Dist: pytest-cov >=4.1 ; extra == "dev"
Requires-Dist: pytest-xdist >= 3.7 ; extra == "dev"
Requires-Dist: ruff >=0.1 ; extra == "dev"
Requires-Dist: sqlalchemy >=2.0 ; extra == "dev"
Requires-Dist: numpydoc >=1.6 ; extra == "docs"
Requires-Dist: sphinx >=7.2 ; extra == "docs"
Requires-Dist: sphinx-copybutton >=0.5 ; extra == "docs"
Requires-Dist: pydata-sphinx-theme >=0.16.1 ; extra == "docs"
Requires-Dist: sphinxcontrib-jquery >=4.1 ; extra == "docs"
Requires-Dist: coverage >=7.3 ; extra == "tests"
Requires-Dist: pyfakefs >=5.3 ; extra == "tests"
Requires-Dist: pytest >=7.4 ; extra == "tests"
Requires-Dist: pytest-cov >=4.1 ; extra == "tests"
Requires-Dist: pytest-xdist >= 3.7 ; extra == "tests"
Requires-Dist: sqlalchemy >=2.0 ; extra == "tests"
Project-URL: documentation, https://pydicom.github.io/pynetdicom
Project-URL: homepage, https://github.com/pydicom/pynetdicom
Provides-Extra: apps
Provides-Extra: dev
Provides-Extra: docs
Provides-Extra: tests
